aip_agents/__init__.py
aip_agents/constants.py
aip_agents/a2a/__init__.py
aip_agents/a2a/types.py
aip_agents/a2a/server/__init__.py
aip_agents/a2a/server/base_executor.py
aip_agents/a2a/server/google_adk_executor.py
aip_agents/a2a/server/langflow_executor.py
aip_agents/a2a/server/langgraph_executor.py
aip_agents/agent/__init__.py
aip_agents/agent/base_agent.py
aip_agents/agent/base_langgraph_agent.py
aip_agents/agent/google_adk_agent.py
aip_agents/agent/google_adk_constants.py
aip_agents/agent/interface.py
aip_agents/agent/interfaces.py
aip_agents/agent/langflow_agent.py
aip_agents/agent/langgraph_memory_enhancer_agent.py
aip_agents/agent/langgraph_react_agent.py
aip_agents/agent/system_instruction_context.py
aip_agents/agent/hitl/__init__.py
aip_agents/agent/hitl/config.py
aip_agents/agent/hitl/langgraph_hitl_mixin.py
aip_agents/agent/hitl/manager.py
aip_agents/agent/hitl/models.py
aip_agents/agent/hitl/registry.py
aip_agents/agent/hitl/prompt/__init__.py
aip_agents/agent/hitl/prompt/base.py
aip_agents/agent/hitl/prompt/deferred.py
aip_agents/clients/__init__.py
aip_agents/clients/langflow/__init__.py
aip_agents/clients/langflow/client.py
aip_agents/clients/langflow/types.py
aip_agents/credentials/manager.py
aip_agents/examples/__init__.py
aip_agents/examples/compare_streaming_client.py
aip_agents/examples/compare_streaming_server.py
aip_agents/examples/hello_world_a2a_google_adk_client.py
aip_agents/examples/hello_world_a2a_google_adk_client_agent.py
aip_agents/examples/hello_world_a2a_google_adk_client_streaming.py
aip_agents/examples/hello_world_a2a_google_adk_server.py
aip_agents/examples/hello_world_a2a_langchain_client.py
aip_agents/examples/hello_world_a2a_langchain_client_agent.py
aip_agents/examples/hello_world_a2a_langchain_client_lm_invoker.py
aip_agents/examples/hello_world_a2a_langchain_client_streaming.py
aip_agents/examples/hello_world_a2a_langchain_reference_client_streaming.py
aip_agents/examples/hello_world_a2a_langchain_reference_server.py
aip_agents_binary-0.6.5.dist-info/METADATA
aip_agents_binary-0.6.5.dist-info/WHEEL
aip_agents_binary-0.6.5.dist-info/top_level.txt
aip_agents_binary-0.6.5.dist-info/RECORD
