Metadata-Version: 2.4
Name: aip-agents-binary
Version: 0.6.5
Summary: A library for managing agents in Gen AI applications.
Author-email: Raymond Christopher <raymond.christopher@gdplabs.id>
Requires-Python: <3.13,>=3.11
Requires-Dist: a2a-sdk<0.3.0,>=0.2.4
Requires-Dist: aiostream<0.7.0,>=0.6.0
Requires-Dist: authlib<2.0.0,>=1.6.4
Requires-Dist: bosa-connectors-binary<0.4.0,>=0.3.1
Requires-Dist: bosa-core-binary[logger,telemetry]<0.10.0,>=0.9.6
Requires-Dist: colorama<0.5.0,>=0.4.6
Requires-Dist: deprecated<2.0.0,>=1.2.18
Requires-Dist: fastapi<0.121.0,>=0.120.0
Requires-Dist: gllm-core-binary<0.4.0,>=0.3.18
Requires-Dist: gllm-inference-binary[anthropic,bedrock,google-genai,google-vertexai,openai]<0.6.0,>=0.5.90
Requires-Dist: gllm-tools-binary<0.2.0,>=0.1.5
Requires-Dist: google-adk<0.6.0,>=0.5.0
Requires-Dist: langchain<0.4.0,>=0.3.0
Requires-Dist: langchain-openai<0.4.0,>=0.3.17
Requires-Dist: langchain-mcp-adapters<0.1.0,>=0.0.10
Requires-Dist: langchain-experimental<0.4.0,>=0.3.4
Requires-Dist: langgraph<0.7.0,>=0.6.0
Requires-Dist: minio<8.0.0,>=7.2.20
Requires-Dist: pydantic<3.0.0,>=2.11.7
Requires-Dist: python-dateutil<3.0.0,>=2.9.0
Requires-Dist: python-dotenv<2.0.0,>=1.1.0
Requires-Dist: requests<3.0.0,>=2.32.4
Requires-Dist: uvicorn<0.35.0,>=0.34.3
Provides-Extra: memory
Requires-Dist: gllm-memory-binary[mem0ai]<0.2.0,>=0.1.1; extra == "memory"
Provides-Extra: privacy
Requires-Dist: gllm-privacy-binary<0.5.0,>=0.4.12; extra == "privacy"
Provides-Extra: guardrails
Requires-Dist: gllm-guardrail-binary<0.1.0,>=0.0.1; extra == "guardrails"
Provides-Extra: gl-connector
Requires-Dist: bosa-connectors-binary<0.4.0,>=0.3.1; extra == "gl-connector"
Provides-Extra: local
Requires-Dist: e2b<3.0.0,>=2.3.0; extra == "local"
Requires-Dist: browser-use==0.5.9; extra == "local"
Requires-Dist: steel-sdk>=0.7.0; extra == "local"
Requires-Dist: json-repair>=0.52.3; extra == "local"
Requires-Dist: PyPDF2<4.0.0,>=3.0.0; extra == "local"
Requires-Dist: unidecode<2.0.0,>=1.3.0; extra == "local"
Requires-Dist: gllm-docproc-binary[docx,pdf,xlsx]<0.8.0,>=0.7.21; extra == "local"
Requires-Dist: gllm-multimodal-binary==0.2.0.post1; extra == "local"
Requires-Dist: bosa-connectors-binary<0.4.0,>=0.3.1; extra == "local"
Provides-Extra: dev
Requires-Dist: coverage<8.0.0,>=7.4.4; extra == "dev"
Requires-Dist: mypy<2.0.0,>=1.15.0; extra == "dev"
Requires-Dist: nest-asyncio<2.0.0,>=1.6.0; extra == "dev"
Requires-Dist: pre-commit<4.0.0,>=3.7.0; extra == "dev"
Requires-Dist: pytest<9.0.0,>=8.1.1; extra == "dev"
Requires-Dist: pytest-asyncio<0.24.0,>=0.23.6; extra == "dev"
Requires-Dist: pytest-cov<6.0.0,>=5.0.0; extra == "dev"
Requires-Dist: pytest-xdist>=3.8.0; extra == "dev"
Requires-Dist: ruff<0.7.0,>=0.6.7; extra == "dev"
Requires-Dist: pillow<12.0.0,>=11.3.0; extra == "dev"
